zsp/__init__.py
zsp-0.0.1.dist-info/LICENSE
zsp-0.0.1.dist-info/METADATA
zsp-0.0.1.dist-info/WHEEL
zsp-0.0.1.dist-info/top_level.txt
zsp-0.0.1.dist-info/RECORD
