Metadata-Version: 2.1
Name: zsp
Version: 0.0.1
Summary: zsp
Home-page: https://github.com/lab-zymon/zsp
Author: Szymon Woźniak
Author-email: s@zymon.org
License: UNKNOWN
Platform: UNKNOWN
Requires-Python: >=3.7
